geotriangulate/__init__.py
geotriangulate/geotriangulate.py
geotriangulate-1.0.1.dist-info/LICENSE.txt
geotriangulate-1.0.1.dist-info/METADATA
geotriangulate-1.0.1.dist-info/WHEEL
geotriangulate-1.0.1.dist-info/top_level.txt
geotriangulate-1.0.1.dist-info/RECORD
