Metadata-Version: 2.1
Name: geotriangulate
Version: 1.0.1
Summary: geotriangulate
Home-page: https://github.com/hashdrd/geotriangulate
Author: my_nickname
Author-email: example@gmail.com
License: UNKNOWN
Project-URL: Documentation, https://github.com/hashdrd/geotriangulate
Platform: UNKNOWN
Classifier: Programming Language :: Python :: 3.9
Classifier: License :: OSI Approved :: MIT License
Classifier: Operating System :: OS Independent
Requires-Python: >=3.7
License-File: LICENSE.txt
Requires-Dist: requests >=2.25.1
